{
  "timestamp": "2026-07-19T11:55:01.965444",
  "data": [
    {
      "entity_id": "sensor.eta_192_168_178_89_sys_aussentemperatur",
      "state": "22.7",
      "attributes": {
        "state_class": "measurement",
        "unit_of_measurement": "\u00b0C",
        "device_class": "temperature",
        "friendly_name": "Au\u00dfentemperatur"
      },
      "last_changed": "2026-07-19T09:54:31.962152+00:00",
      "last_reported": "2026-07-19T09:54:31.962152+00:00",
      "last_updated": "2026-07-19T09:54:31.962152+00:00",
      "context": {
        "id": "01KXWWRYWTBZJ7NZR1BNH61KF0",
        "parent_id": null,
        "user_id": null
      }
    },
    {
      "entity_id": "sensor.pv_power",
      "state": "4561",
      "attributes": {
        "state_class": "measurement",
        "unit_of_measurement": "W",
        "device_class": "power",
        "icon": "mdi:solar-power",
        "friendly_name": "aktuelle PV Leistung"
      },
      "last_changed": "2026-07-19T09:54:59.410063+00:00",
      "last_reported": "2026-07-19T09:54:59.410063+00:00",
      "last_updated": "2026-07-19T09:54:59.410063+00:00",
      "context": {
        "id": "01KXWWSSPJFH3AA9DA6D5N8E94",
        "parent_id": null,
        "user_id": null
      }
    },
    {
      "entity_id": "sensor.active_power",
      "state": "4108",
      "attributes": {
        "state_class": "measurement",
        "unit_of_measurement": "W",
        "device_class": "power",
        "icon": "mdi:transmission-tower",
        "friendly_name": "aktuelle Netzeinspeisung"
      },
      "last_changed": "2026-07-19T09:54:59.412698+00:00",
      "last_reported": "2026-07-19T09:54:59.412698+00:00",
      "last_updated": "2026-07-19T09:54:59.412698+00:00",
      "context": {
        "id": "01KXWWSSPMDJZWXDZE4NZK9J53",
        "parent_id": null,
        "user_id": null
      }
    },
    {
      "entity_id": "sensor.house_consumption",
      "state": "421",
      "attributes": {
        "state_class": "measurement",
        "unit_of_measurement": "W",
        "device_class": "power",
        "icon": "mdi:power-plug-outline",
        "friendly_name": "aktueller Verbrauch"
      },
      "last_changed": "2026-07-19T09:54:59.429738+00:00",
      "last_reported": "2026-07-19T09:54:59.429738+00:00",
      "last_updated": "2026-07-19T09:54:59.429738+00:00",
      "context": {
        "id": "01KXWWSSQ5VNWMXAYMAX7HD2MH",
        "parent_id": null,
        "user_id": null
      }
    },
    {
      "entity_id": "sensor.battery_state_of_charge",
      "state": "100",
      "attributes": {
        "state_class": "measurement",
        "unit_of_measurement": "%",
        "device_class": "battery",
        "icon": "mdi:battery-high",
        "friendly_name": "Ladezustand Batterie"
      },
      "last_changed": "2026-07-19T09:16:59.430026+00:00",
      "last_reported": "2026-07-19T09:19:59.437658+00:00",
      "last_updated": "2026-07-19T09:16:59.430026+00:00",
      "context": {
        "id": "01KXWTM756QBRZ25SESEPCPRKG",
        "parent_id": null,
        "user_id": null
      }
    }
  ]
}