{
  "timestamp": "2026-05-24T08:30:02.570724",
  "data": [
    {
      "entity_id": "sensor.pv_power",
      "state": "254",
      "attributes": {
        "state_class": "measurement",
        "unit_of_measurement": "W",
        "device_class": "power",
        "icon": "mdi:solar-power",
        "friendly_name": "aktuelle PV Leistung"
      },
      "last_changed": "2026-05-24T06:29:26.930026+00:00",
      "last_reported": "2026-05-24T06:29:26.930026+00:00",
      "last_updated": "2026-05-24T06:29:26.930026+00:00",
      "context": {
        "id": "01KSCAS68JWPSB2TDCNX3Z5KCR",
        "parent_id": null,
        "user_id": null
      }
    },
    {
      "entity_id": "sensor.active_power",
      "state": "10",
      "attributes": {
        "state_class": "measurement",
        "unit_of_measurement": "W",
        "device_class": "power",
        "icon": "mdi:transmission-tower",
        "friendly_name": "aktuelle Netzeinspeisung"
      },
      "last_changed": "2026-05-24T06:29:56.918433+00:00",
      "last_reported": "2026-05-24T06:29:56.918433+00:00",
      "last_updated": "2026-05-24T06:29:56.918433+00:00",
      "context": {
        "id": "01KSCAT3HP6D1VPNHF2AKS52T9",
        "parent_id": null,
        "user_id": null
      }
    },
    {
      "entity_id": "sensor.house_consumption",
      "state": "798",
      "attributes": {
        "state_class": "measurement",
        "unit_of_measurement": "W",
        "device_class": "power",
        "icon": "mdi:power-plug-outline",
        "friendly_name": "aktueller Verbrauch"
      },
      "last_changed": "2026-05-24T06:29:44.929293+00:00",
      "last_reported": "2026-05-24T06:29:44.929293+00:00",
      "last_updated": "2026-05-24T06:29:44.929293+00:00",
      "context": {
        "id": "01KSCASQV11TS3J71233JP78JH",
        "parent_id": null,
        "user_id": null
      }
    },
    {
      "entity_id": "sensor.battery_state_of_charge",
      "state": "24",
      "attributes": {
        "state_class": "measurement",
        "unit_of_measurement": "%",
        "device_class": "battery",
        "icon": "mdi:battery-high",
        "friendly_name": "Ladezustand Batterie"
      },
      "last_changed": "2026-05-24T06:16:35.946265+00:00",
      "last_reported": "2026-05-24T06:16:35.946265+00:00",
      "last_updated": "2026-05-24T06:16:35.946265+00:00",
      "context": {
        "id": "01KSCA1NBA8A7KTJGFXAYT726D",
        "parent_id": null,
        "user_id": null
      }
    },
    {
      "entity_id": "sensor.eta_sys_aussentemperatur",
      "state": "17.8",
      "attributes": {
        "state_class": "measurement",
        "unit_of_measurement": "\u00b0C",
        "device_class": "temperature",
        "friendly_name": "Au\u00dfentemperatur"
      },
      "last_changed": "2026-05-24T06:29:46.567292+00:00",
      "last_reported": "2026-05-24T06:29:46.567292+00:00",
      "last_updated": "2026-05-24T06:29:46.567292+00:00",
      "context": {
        "id": "01KSCASSE76FEVRPTM27HN76RX",
        "parent_id": null,
        "user_id": null
      }
    }
  ]
}