{
  "timestamp": "2026-07-20T08:10:02.346388",
  "data": [
    {
      "entity_id": "sensor.eta_192_168_178_89_sys_aussentemperatur",
      "state": "14.0",
      "attributes": {
        "state_class": "measurement",
        "unit_of_measurement": "\u00b0C",
        "device_class": "temperature",
        "friendly_name": "Au\u00dfentemperatur"
      },
      "last_changed": "2026-07-20T06:07:31.967940+00:00",
      "last_reported": "2026-07-20T06:09:31.964843+00:00",
      "last_updated": "2026-07-20T06:07:31.967940+00:00",
      "context": {
        "id": "01KXZ2613ZCK61VYAN7872NFCP",
        "parent_id": null,
        "user_id": null
      }
    },
    {
      "entity_id": "sensor.pv_power",
      "state": "264",
      "attributes": {
        "state_class": "measurement",
        "unit_of_measurement": "W",
        "device_class": "power",
        "icon": "mdi:solar-power",
        "friendly_name": "aktuelle PV Leistung"
      },
      "last_changed": "2026-07-20T05:56:01.408117+00:00",
      "last_reported": "2026-07-20T05:56:11.404892+00:00",
      "last_updated": "2026-07-20T05:56:01.408117+00:00",
      "context": {
        "id": "01KXZ1GYR0AWVR1JMY38SBZMTA",
        "parent_id": null,
        "user_id": null
      }
    },
    {
      "entity_id": "sensor.active_power",
      "state": "-17",
      "attributes": {
        "state_class": "measurement",
        "unit_of_measurement": "W",
        "device_class": "power",
        "icon": "mdi:transmission-tower",
        "friendly_name": "aktuelle Netzeinspeisung"
      },
      "last_changed": "2026-07-20T06:09:57.417539+00:00",
      "last_reported": "2026-07-20T06:09:57.417539+00:00",
      "last_updated": "2026-07-20T06:09:57.417539+00:00",
      "context": {
        "id": "01KXZ2AF59B4BFZ2AMSV4FZXW2",
        "parent_id": null,
        "user_id": null
      }
    },
    {
      "entity_id": "sensor.house_consumption",
      "state": "1222",
      "attributes": {
        "state_class": "measurement",
        "unit_of_measurement": "W",
        "device_class": "power",
        "icon": "mdi:power-plug-outline",
        "friendly_name": "aktueller Verbrauch"
      },
      "last_changed": "2026-07-20T06:09:57.434326+00:00",
      "last_reported": "2026-07-20T06:09:57.434326+00:00",
      "last_updated": "2026-07-20T06:09:57.434326+00:00",
      "context": {
        "id": "01KXZ2AF5T08FJBF7JXY5JH81S",
        "parent_id": null,
        "user_id": null
      }
    },
    {
      "entity_id": "sensor.battery_state_of_charge",
      "state": "23",
      "attributes": {
        "state_class": "measurement",
        "unit_of_measurement": "%",
        "device_class": "battery",
        "icon": "mdi:battery-high",
        "friendly_name": "Ladezustand Batterie"
      },
      "last_changed": "2026-07-20T06:08:47.429718+00:00",
      "last_reported": "2026-07-20T06:09:57.439124+00:00",
      "last_updated": "2026-07-20T06:08:47.429718+00:00",
      "context": {
        "id": "01KXZ28AT5R1B61BCASKBKF796",
        "parent_id": null,
        "user_id": null
      }
    }
  ]
}