{
  "timestamp": "2026-05-06T01:30:02.212249",
  "data": [
    {
      "entity_id": "sensor.pv_power",
      "state": "0",
      "attributes": {
        "state_class": "measurement",
        "unit_of_measurement": "W",
        "device_class": "power",
        "icon": "mdi:solar-power",
        "friendly_name": "aktuelle PV Leistung"
      },
      "last_changed": "2026-05-05T18:33:27.828274+00:00",
      "last_reported": "2026-05-05T18:35:01.822322+00:00",
      "last_updated": "2026-05-05T18:33:27.828274+00:00",
      "context": {
        "id": "01KQWPN80MZV66MF9715AX1BSD",
        "parent_id": null,
        "user_id": null
      }
    },
    {
      "entity_id": "sensor.active_power",
      "state": "-206",
      "attributes": {
        "state_class": "measurement",
        "unit_of_measurement": "W",
        "device_class": "power",
        "icon": "mdi:transmission-tower",
        "friendly_name": "aktuelle Netzeinspeisung"
      },
      "last_changed": "2026-05-05T23:30:00.823408+00:00",
      "last_reported": "2026-05-05T23:30:00.823408+00:00",
      "last_updated": "2026-05-05T23:30:00.823408+00:00",
      "context": {
        "id": "01KQX7M7ZQXJ70T6DHGEJS0CW9",
        "parent_id": null,
        "user_id": null
      }
    },
    {
      "entity_id": "sensor.house_consumption",
      "state": "190",
      "attributes": {
        "state_class": "measurement",
        "unit_of_measurement": "W",
        "device_class": "power",
        "icon": "mdi:power-plug-outline",
        "friendly_name": "aktueller Verbrauch"
      },
      "last_changed": "2026-05-05T23:30:00.834486+00:00",
      "last_reported": "2026-05-05T23:30:00.834486+00:00",
      "last_updated": "2026-05-05T23:30:00.834486+00:00",
      "context": {
        "id": "01KQX7M8022MQ57N79QQ0HFFDA",
        "parent_id": null,
        "user_id": null
      }
    },
    {
      "entity_id": "sensor.battery_state_of_charge",
      "state": "5",
      "attributes": {
        "state_class": "measurement",
        "unit_of_measurement": "%",
        "device_class": "battery",
        "icon": "mdi:battery-high",
        "friendly_name": "Ladezustand Batterie"
      },
      "last_changed": "2026-05-05T19:19:48.843189+00:00",
      "last_reported": "2026-05-05T19:19:58.848040+00:00",
      "last_updated": "2026-05-05T19:19:48.843189+00:00",
      "context": {
        "id": "01KQWSA3VBZ8GCXW2BX3KKFYWP",
        "parent_id": null,
        "user_id": null
      }
    },
    {
      "entity_id": "sensor.eta_sys_aussentemperatur",
      "state": "12.7",
      "attributes": {
        "state_class": "measurement",
        "unit_of_measurement": "\u00b0C",
        "device_class": "temperature",
        "friendly_name": "Au\u00dfentemperatur"
      },
      "last_changed": "2026-05-05T23:18:11.074964+00:00",
      "last_reported": "2026-05-05T23:19:11.068340+00:00",
      "last_updated": "2026-05-05T23:18:11.074964+00:00",
      "context": {
        "id": "01KQX6YJW26JB9V8SKBBVQ0CB4",
        "parent_id": null,
        "user_id": null
      }
    }
  ]
}