{
  "timestamp": "2026-05-07T10:50:02.199709",
  "data": [
    {
      "entity_id": "sensor.pv_power",
      "state": "1188",
      "attributes": {
        "state_class": "measurement",
        "unit_of_measurement": "W",
        "device_class": "power",
        "icon": "mdi:solar-power",
        "friendly_name": "aktuelle PV Leistung"
      },
      "last_changed": "2026-05-07T08:50:01.829375+00:00",
      "last_reported": "2026-05-07T08:50:01.829375+00:00",
      "last_updated": "2026-05-07T08:50:01.829375+00:00",
      "context": {
        "id": "01KR0T2CF5F6TGVH755D31WWH6",
        "parent_id": null,
        "user_id": null
      }
    },
    {
      "entity_id": "sensor.active_power",
      "state": "29",
      "attributes": {
        "state_class": "measurement",
        "unit_of_measurement": "W",
        "device_class": "power",
        "icon": "mdi:transmission-tower",
        "friendly_name": "aktuelle Netzeinspeisung"
      },
      "last_changed": "2026-05-07T08:50:01.831584+00:00",
      "last_reported": "2026-05-07T08:50:01.831584+00:00",
      "last_updated": "2026-05-07T08:50:01.831584+00:00",
      "context": {
        "id": "01KR0T2CF779BM7ZK50HZMFTR5",
        "parent_id": null,
        "user_id": null
      }
    },
    {
      "entity_id": "sensor.house_consumption",
      "state": "281",
      "attributes": {
        "state_class": "measurement",
        "unit_of_measurement": "W",
        "device_class": "power",
        "icon": "mdi:power-plug-outline",
        "friendly_name": "aktueller Verbrauch"
      },
      "last_changed": "2026-05-07T08:50:01.842731+00:00",
      "last_reported": "2026-05-07T08:50:01.842731+00:00",
      "last_updated": "2026-05-07T08:50:01.842731+00:00",
      "context": {
        "id": "01KR0T2CFJMEB92CB9H6E9BMWC",
        "parent_id": null,
        "user_id": null
      }
    },
    {
      "entity_id": "sensor.battery_state_of_charge",
      "state": "22",
      "attributes": {
        "state_class": "measurement",
        "unit_of_measurement": "%",
        "device_class": "battery",
        "icon": "mdi:battery-high",
        "friendly_name": "Ladezustand Batterie"
      },
      "last_changed": "2026-05-07T08:47:08.846613+00:00",
      "last_reported": "2026-05-07T08:50:01.852268+00:00",
      "last_updated": "2026-05-07T08:47:08.846613+00:00",
      "context": {
        "id": "01KR0SX3HECTEJ6HG22VTBQGYR",
        "parent_id": null,
        "user_id": null
      }
    },
    {
      "entity_id": "sensor.eta_sys_aussentemperatur",
      "state": "15.2",
      "attributes": {
        "state_class": "measurement",
        "unit_of_measurement": "\u00b0C",
        "device_class": "temperature",
        "friendly_name": "Au\u00dfentemperatur"
      },
      "last_changed": "2026-05-07T08:48:14.188585+00:00",
      "last_reported": "2026-05-07T08:49:14.163928+00:00",
      "last_updated": "2026-05-07T08:48:14.188585+00:00",
      "context": {
        "id": "01KR0SZ3BCK2CAQ1N3BH1NZC5D",
        "parent_id": null,
        "user_id": null
      }
    }
  ]
}