{
  "timestamp": "2026-07-13T11:05:02.038317",
  "data": [
    {
      "entity_id": "sensor.eta_192_168_178_89_sys_aussentemperatur",
      "state": "31.6",
      "attributes": {
        "state_class": "measurement",
        "unit_of_measurement": "\u00b0C",
        "device_class": "temperature",
        "friendly_name": "Au\u00dfentemperatur"
      },
      "last_changed": "2026-07-13T09:04:25.957502+00:00",
      "last_reported": "2026-07-13T09:04:25.957502+00:00",
      "last_updated": "2026-07-13T09:04:25.957502+00:00",
      "context": {
        "id": "01KXDBGXB5TBMMDRAXSTYA271Y",
        "parent_id": null,
        "user_id": null
      }
    },
    {
      "entity_id": "sensor.pv_power",
      "state": "2738",
      "attributes": {
        "state_class": "measurement",
        "unit_of_measurement": "W",
        "device_class": "power",
        "icon": "mdi:solar-power",
        "friendly_name": "aktuelle PV Leistung"
      },
      "last_changed": "2026-07-13T09:04:57.411308+00:00",
      "last_reported": "2026-07-13T09:04:57.411308+00:00",
      "last_updated": "2026-07-13T09:04:57.411308+00:00",
      "context": {
        "id": "01KXDBHW23VBEGDBZJK0QCY8G1",
        "parent_id": null,
        "user_id": null
      }
    },
    {
      "entity_id": "sensor.active_power",
      "state": "10",
      "attributes": {
        "state_class": "measurement",
        "unit_of_measurement": "W",
        "device_class": "power",
        "icon": "mdi:transmission-tower",
        "friendly_name": "aktuelle Netzeinspeisung"
      },
      "last_changed": "2026-07-13T09:04:57.421494+00:00",
      "last_reported": "2026-07-13T09:04:57.421494+00:00",
      "last_updated": "2026-07-13T09:04:57.421494+00:00",
      "context": {
        "id": "01KXDBHW2DSR4FC0GRCB8SXTNJ",
        "parent_id": null,
        "user_id": null
      }
    },
    {
      "entity_id": "sensor.house_consumption",
      "state": "1934",
      "attributes": {
        "state_class": "measurement",
        "unit_of_measurement": "W",
        "device_class": "power",
        "icon": "mdi:power-plug-outline",
        "friendly_name": "aktueller Verbrauch"
      },
      "last_changed": "2026-07-13T09:04:57.434593+00:00",
      "last_reported": "2026-07-13T09:04:57.434593+00:00",
      "last_updated": "2026-07-13T09:04:57.434593+00:00",
      "context": {
        "id": "01KXDBHW2TBH0B29DZ6GGDWVHF",
        "parent_id": null,
        "user_id": null
      }
    },
    {
      "entity_id": "sensor.battery_state_of_charge",
      "state": "58",
      "attributes": {
        "state_class": "measurement",
        "unit_of_measurement": "%",
        "device_class": "battery",
        "icon": "mdi:battery-high",
        "friendly_name": "Ladezustand Batterie"
      },
      "last_changed": "2026-07-13T09:03:16.456148+00:00",
      "last_reported": "2026-07-13T09:03:16.456148+00:00",
      "last_updated": "2026-07-13T09:03:16.456148+00:00",
      "context": {
        "id": "01KXDBESF82SRKX22R1YZPFJAQ",
        "parent_id": null,
        "user_id": null
      }
    }
  ]
}