[
  {
    "timestamp": "2026-07-10T07:05:02.003963",
    "values": {
      "sensor.pv_power": 150.0,
      "sensor.active_power": 1882.0,
      "sensor.house_consumption": -45.0,
      "sensor.battery_state_of_charge": 48.0
    }
  },
  {
    "timestamp": "2026-07-10T07:10:02.051321",
    "values": {
      "sensor.pv_power": 150.0,
      "sensor.active_power": -32.0,
      "sensor.house_consumption": 162.0,
      "sensor.battery_state_of_charge": 48.0
    }
  },
  {
    "timestamp": "2026-07-10T07:15:02.121423",
    "values": {
      "sensor.pv_power": 150.0,
      "sensor.active_power": 73.0,
      "sensor.house_consumption": 178.0,
      "sensor.battery_state_of_charge": 48.0
    }
  },
  {
    "timestamp": "2026-07-10T07:15:02.196203",
    "values": {
      "sensor.pv_power": 150.0,
      "sensor.active_power": 73.0,
      "sensor.house_consumption": 178.0,
      "sensor.battery_state_of_charge": 48.0
    }
  },
  {
    "timestamp": "2026-07-10T07:20:01.716130",
    "values": {
      "sensor.pv_power": 169.0,
      "sensor.active_power": 11.0,
      "sensor.house_consumption": 211.0,
      "sensor.battery_state_of_charge": 48.0
    }
  },
  {
    "timestamp": "2026-07-10T07:25:02.709867",
    "values": {
      "sensor.pv_power": 169.0,
      "sensor.active_power": -3.0,
      "sensor.house_consumption": 282.0,
      "sensor.battery_state_of_charge": 48.0
    }
  },
  {
    "timestamp": "2026-07-10T07:30:02.218647",
    "values": {
      "sensor.pv_power": 188.0,
      "sensor.active_power": 8.0,
      "sensor.house_consumption": 235.0,
      "sensor.battery_state_of_charge": 48.0
    }
  },
  {
    "timestamp": "2026-07-10T07:30:02.310824",
    "values": {
      "sensor.pv_power": 188.0,
      "sensor.active_power": 8.0,
      "sensor.house_consumption": 235.0,
      "sensor.battery_state_of_charge": 48.0
    }
  },
  {
    "timestamp": "2026-07-10T07:35:01.831348",
    "values": {
      "sensor.pv_power": 177.0,
      "sensor.active_power": 1.0,
      "sensor.house_consumption": 232.0,
      "sensor.battery_state_of_charge": 48.0
    }
  },
  {
    "timestamp": "2026-07-10T07:40:04.900192",
    "values": {
      "sensor.pv_power": 188.0,
      "sensor.active_power": -4.0,
      "sensor.house_consumption": 348.0,
      "sensor.battery_state_of_charge": 47.0
    }
  },
  {
    "timestamp": "2026-07-10T07:45:04.229030",
    "values": {
      "sensor.pv_power": 188.0,
      "sensor.active_power": 61.0,
      "sensor.house_consumption": 290.0,
      "sensor.battery_state_of_charge": 47.0
    }
  },
  {
    "timestamp": "2026-07-10T07:45:04.326101",
    "values": {
      "sensor.pv_power": 188.0,
      "sensor.active_power": 61.0,
      "sensor.house_consumption": 290.0,
      "sensor.battery_state_of_charge": 47.0
    }
  },
  {
    "timestamp": "2026-07-10T07:50:01.758962",
    "values": {
      "sensor.pv_power": 207.0,
      "sensor.active_power": 23.0,
      "sensor.house_consumption": 456.0,
      "sensor.battery_state_of_charge": 45.0
    }
  },
  {
    "timestamp": "2026-07-10T07:55:02.607546",
    "values": {
      "sensor.pv_power": 207.0,
      "sensor.active_power": -1.0,
      "sensor.house_consumption": 362.0,
      "sensor.battery_state_of_charge": 44.0
    }
  },
  {
    "timestamp": "2026-07-10T08:00:01.673464",
    "values": {
      "sensor.pv_power": 207.0,
      "sensor.active_power": 34.0,
      "sensor.house_consumption": 308.0,
      "sensor.battery_state_of_charge": 43.0
    }
  },
  {
    "timestamp": "2026-07-10T08:00:01.788141",
    "values": {
      "sensor.pv_power": 207.0,
      "sensor.active_power": 34.0,
      "sensor.house_consumption": 308.0,
      "sensor.battery_state_of_charge": 43.0
    }
  },
  {
    "timestamp": "2026-07-10T08:05:04.429026",
    "values": {
      "sensor.pv_power": 226.0,
      "sensor.active_power": 1.0,
      "sensor.house_consumption": 379.0,
      "sensor.battery_state_of_charge": 43.0
    }
  },
  {
    "timestamp": "2026-07-10T08:10:01.989448",
    "values": {
      "sensor.pv_power": 226.0,
      "sensor.active_power": -81.0,
      "sensor.house_consumption": 423.0,
      "sensor.battery_state_of_charge": 43.0
    }
  },
  {
    "timestamp": "2026-07-10T08:15:03.156677",
    "values": {
      "sensor.pv_power": 226.0,
      "sensor.active_power": 25.0,
      "sensor.house_consumption": 316.0,
      "sensor.battery_state_of_charge": 43.0
    }
  },
  {
    "timestamp": "2026-07-10T08:15:03.305793",
    "values": {
      "sensor.pv_power": 226.0,
      "sensor.active_power": 25.0,
      "sensor.house_consumption": 316.0,
      "sensor.battery_state_of_charge": 43.0
    }
  },
  {
    "timestamp": "2026-07-10T08:20:02.153417",
    "values": {
      "sensor.pv_power": 226.0,
      "sensor.active_power": 109.0,
      "sensor.house_consumption": 2635.0,
      "sensor.battery_state_of_charge": 41.0
    }
  },
  {
    "timestamp": "2026-07-10T08:25:03.364570",
    "values": {
      "sensor.pv_power": 226.0,
      "sensor.active_power": -87.0,
      "sensor.house_consumption": 2711.0,
      "sensor.battery_state_of_charge": 38.0
    }
  },
  {
    "timestamp": "2026-07-10T08:30:01.976413",
    "values": {
      "sensor.pv_power": 245.0,
      "sensor.active_power": -62.0,
      "sensor.house_consumption": 2859.0,
      "sensor.battery_state_of_charge": 35.0
    }
  },
  {
    "timestamp": "2026-07-10T08:30:02.026146",
    "values": {
      "sensor.pv_power": 245.0,
      "sensor.active_power": -62.0,
      "sensor.house_consumption": 2859.0,
      "sensor.battery_state_of_charge": 35.0
    }
  },
  {
    "timestamp": "2026-07-10T08:35:04.811261",
    "values": {
      "sensor.pv_power": 245.0,
      "sensor.active_power": 140.0,
      "sensor.house_consumption": 336.0,
      "sensor.battery_state_of_charge": 34.0
    }
  },
  {
    "timestamp": "2026-07-10T08:40:03.139400",
    "values": {
      "sensor.pv_power": 245.0,
      "sensor.active_power": 48.0,
      "sensor.house_consumption": 292.0,
      "sensor.battery_state_of_charge": 34.0
    }
  },
  {
    "timestamp": "2026-07-10T08:45:02.231142",
    "values": {
      "sensor.pv_power": 245.0,
      "sensor.active_power": 77.0,
      "sensor.house_consumption": 408.0,
      "sensor.battery_state_of_charge": 34.0
    }
  },
  {
    "timestamp": "2026-07-10T08:45:02.276031",
    "values": {
      "sensor.pv_power": 245.0,
      "sensor.active_power": 77.0,
      "sensor.house_consumption": 408.0,
      "sensor.battery_state_of_charge": 34.0
    }
  },
  {
    "timestamp": "2026-07-10T08:50:02.560430",
    "values": {
      "sensor.pv_power": 245.0,
      "sensor.active_power": 96.0,
      "sensor.house_consumption": 265.0,
      "sensor.battery_state_of_charge": 34.0
    }
  },
  {
    "timestamp": "2026-07-10T08:55:01.984413",
    "values": {
      "sensor.pv_power": 264.0,
      "sensor.active_power": -20.0,
      "sensor.house_consumption": 263.0,
      "sensor.battery_state_of_charge": 33.0
    }
  },
  {
    "timestamp": "2026-07-10T09:00:02.447089",
    "values": {
      "sensor.pv_power": 264.0,
      "sensor.active_power": 5.0,
      "sensor.house_consumption": 2454.0,
      "sensor.battery_state_of_charge": 32.0
    }
  },
  {
    "timestamp": "2026-07-10T09:00:02.514144",
    "values": {
      "sensor.pv_power": 264.0,
      "sensor.active_power": 5.0,
      "sensor.house_consumption": 2454.0,
      "sensor.battery_state_of_charge": 32.0
    }
  },
  {
    "timestamp": "2026-07-10T09:05:06.354784",
    "values": {
      "sensor.pv_power": 283.0,
      "sensor.active_power": 90.0,
      "sensor.house_consumption": 310.0,
      "sensor.battery_state_of_charge": 32.0
    }
  },
  {
    "timestamp": "2026-07-10T09:10:02.650695",
    "values": {
      "sensor.pv_power": 302.0,
      "sensor.active_power": -110.0,
      "sensor.house_consumption": 562.0,
      "sensor.battery_state_of_charge": 31.0
    }
  },
  {
    "timestamp": "2026-07-10T09:15:02.105915",
    "values": {
      "sensor.pv_power": 435.0,
      "sensor.active_power": 32.0,
      "sensor.house_consumption": 383.0,
      "sensor.battery_state_of_charge": 31.0
    }
  },
  {
    "timestamp": "2026-07-10T09:15:02.132452",
    "values": {
      "sensor.pv_power": 435.0,
      "sensor.active_power": 32.0,
      "sensor.house_consumption": 383.0,
      "sensor.battery_state_of_charge": 31.0
    }
  },
  {
    "timestamp": "2026-07-10T09:20:02.005876",
    "values": {
      "sensor.pv_power": 528.0,
      "sensor.active_power": 2.0,
      "sensor.house_consumption": 458.0,
      "sensor.battery_state_of_charge": 31.0
    }
  },
  {
    "timestamp": "2026-07-10T09:25:02.237071",
    "values": {
      "sensor.pv_power": 632.0,
      "sensor.active_power": -179.0,
      "sensor.house_consumption": 512.0,
      "sensor.battery_state_of_charge": 31.0
    }
  },
  {
    "timestamp": "2026-07-10T09:30:02.348407",
    "values": {
      "sensor.pv_power": 769.0,
      "sensor.active_power": 57.0,
      "sensor.house_consumption": 535.0,
      "sensor.battery_state_of_charge": 31.0
    }
  },
  {
    "timestamp": "2026-07-10T09:30:02.455655",
    "values": {
      "sensor.pv_power": 769.0,
      "sensor.active_power": 57.0,
      "sensor.house_consumption": 535.0,
      "sensor.battery_state_of_charge": 31.0
    }
  },
  {
    "timestamp": "2026-07-10T09:35:03.039725",
    "values": {
      "sensor.pv_power": 869.0,
      "sensor.active_power": -10.0,
      "sensor.house_consumption": 608.0,
      "sensor.battery_state_of_charge": 32.0
    }
  },
  {
    "timestamp": "2026-07-10T09:40:02.237235",
    "values": {
      "sensor.pv_power": 982.0,
      "sensor.active_power": 90.0,
      "sensor.house_consumption": 374.0,
      "sensor.battery_state_of_charge": 32.0
    }
  },
  {
    "timestamp": "2026-07-10T09:45:05.597170",
    "values": {
      "sensor.pv_power": 1061.0,
      "sensor.active_power": -58.0,
      "sensor.house_consumption": 1404.0,
      "sensor.battery_state_of_charge": 33.0
    }
  },
  {
    "timestamp": "2026-07-10T09:45:05.710550",
    "values": {
      "sensor.pv_power": 1061.0,
      "sensor.active_power": -58.0,
      "sensor.house_consumption": 1404.0,
      "sensor.battery_state_of_charge": 33.0
    }
  },
  {
    "timestamp": "2026-07-10T09:50:03.330555",
    "values": {
      "sensor.pv_power": 1184.0,
      "sensor.active_power": -58.0,
      "sensor.house_consumption": 554.0,
      "sensor.battery_state_of_charge": 33.0
    }
  },
  {
    "timestamp": "2026-07-10T09:55:02.435057",
    "values": {
      "sensor.pv_power": 1352.0,
      "sensor.active_power": 243.0,
      "sensor.house_consumption": 397.0,
      "sensor.battery_state_of_charge": 34.0
    }
  },
  {
    "timestamp": "2026-07-10T10:00:01.809465",
    "values": {
      "sensor.pv_power": 1455.0,
      "sensor.active_power": 46.0,
      "sensor.house_consumption": 548.0,
      "sensor.battery_state_of_charge": 35.0
    }
  },
  {
    "timestamp": "2026-07-10T10:00:01.858757",
    "values": {
      "sensor.pv_power": 1455.0,
      "sensor.active_power": 46.0,
      "sensor.house_consumption": 548.0,
      "sensor.battery_state_of_charge": 35.0
    }
  },
  {
    "timestamp": "2026-07-10T10:05:02.265830",
    "values": {
      "sensor.pv_power": 1543.0,
      "sensor.active_power": -107.0,
      "sensor.house_consumption": 524.0,
      "sensor.battery_state_of_charge": 36.0
    }
  },
  {
    "timestamp": "2026-07-10T10:10:02.421477",
    "values": {
      "sensor.pv_power": 1657.0,
      "sensor.active_power": 2.0,
      "sensor.house_consumption": 507.0,
      "sensor.battery_state_of_charge": 38.0
    }
  },
  {
    "timestamp": "2026-07-10T10:15:01.659697",
    "values": {
      "sensor.pv_power": 1774.0,
      "sensor.active_power": 49.0,
      "sensor.house_consumption": 524.0,
      "sensor.battery_state_of_charge": 39.0
    }
  },
  {
    "timestamp": "2026-07-10T10:15:01.689853",
    "values": {
      "sensor.pv_power": 1774.0,
      "sensor.active_power": 49.0,
      "sensor.house_consumption": 524.0,
      "sensor.battery_state_of_charge": 39.0
    }
  },
  {
    "timestamp": "2026-07-10T10:20:02.593733",
    "values": {
      "sensor.pv_power": 1879.0,
      "sensor.active_power": -22.0,
      "sensor.house_consumption": 554.0,
      "sensor.battery_state_of_charge": 41.0
    }
  },
  {
    "timestamp": "2026-07-10T10:25:01.796509",
    "values": {
      "sensor.pv_power": 2138.0,
      "sensor.active_power": 141.0,
      "sensor.house_consumption": 452.0,
      "sensor.battery_state_of_charge": 42.0
    }
  },
  {
    "timestamp": "2026-07-10T10:30:02.369788",
    "values": {
      "sensor.pv_power": 2352.0,
      "sensor.active_power": 100.0,
      "sensor.house_consumption": 459.0,
      "sensor.battery_state_of_charge": 44.0
    }
  },
  {
    "timestamp": "2026-07-10T10:30:02.401855",
    "values": {
      "sensor.pv_power": 2352.0,
      "sensor.active_power": 100.0,
      "sensor.house_consumption": 459.0,
      "sensor.battery_state_of_charge": 44.0
    }
  },
  {
    "timestamp": "2026-07-10T10:35:02.900348",
    "values": {
      "sensor.pv_power": 2491.0,
      "sensor.active_power": 24.0,
      "sensor.house_consumption": 499.0,
      "sensor.battery_state_of_charge": 46.0
    }
  },
  {
    "timestamp": "2026-07-10T10:40:01.916787",
    "values": {
      "sensor.pv_power": 2609.0,
      "sensor.active_power": 147.0,
      "sensor.house_consumption": 483.0,
      "sensor.battery_state_of_charge": 48.0
    }
  },
  {
    "timestamp": "2026-07-10T10:45:02.026256",
    "values": {
      "sensor.pv_power": 2723.0,
      "sensor.active_power": 44.0,
      "sensor.house_consumption": 421.0,
      "sensor.battery_state_of_charge": 50.0
    }
  },
  {
    "timestamp": "2026-07-10T10:45:02.244359",
    "values": {
      "sensor.pv_power": 2723.0,
      "sensor.active_power": 44.0,
      "sensor.house_consumption": 421.0,
      "sensor.battery_state_of_charge": 50.0
    }
  },
  {
    "timestamp": "2026-07-10T10:50:02.832087",
    "values": {
      "sensor.pv_power": 2844.0,
      "sensor.active_power": -45.0,
      "sensor.house_consumption": 568.0,
      "sensor.battery_state_of_charge": 53.0
    }
  },
  {
    "timestamp": "2026-07-10T10:55:04.122424",
    "values": {
      "sensor.pv_power": 2942.0,
      "sensor.active_power": -33.0,
      "sensor.house_consumption": 632.0,
      "sensor.battery_state_of_charge": 55.0
    }
  },
  {
    "timestamp": "2026-07-10T11:00:02.543946",
    "values": {
      "sensor.pv_power": 3138.0,
      "sensor.active_power": 22.0,
      "sensor.house_consumption": 513.0,
      "sensor.battery_state_of_charge": 57.0
    }
  },
  {
    "timestamp": "2026-07-10T11:00:02.710276",
    "values": {
      "sensor.pv_power": 3138.0,
      "sensor.active_power": 22.0,
      "sensor.house_consumption": 513.0,
      "sensor.battery_state_of_charge": 57.0
    }
  },
  {
    "timestamp": "2026-07-10T11:05:01.827254",
    "values": {
      "sensor.pv_power": 3239.0,
      "sensor.active_power": 177.0,
      "sensor.house_consumption": 2112.0,
      "sensor.battery_state_of_charge": 59.0
    }
  },
  {
    "timestamp": "2026-07-10T11:10:02.185801",
    "values": {
      "sensor.pv_power": 3357.0,
      "sensor.active_power": 20.0,
      "sensor.house_consumption": 570.0,
      "sensor.battery_state_of_charge": 61.0
    }
  },
  {
    "timestamp": "2026-07-10T11:15:02.570968",
    "values": {
      "sensor.pv_power": 3454.0,
      "sensor.active_power": -17.0,
      "sensor.house_consumption": 656.0,
      "sensor.battery_state_of_charge": 64.0
    }
  },
  {
    "timestamp": "2026-07-10T11:15:02.627503",
    "values": {
      "sensor.pv_power": 3454.0,
      "sensor.active_power": -17.0,
      "sensor.house_consumption": 656.0,
      "sensor.battery_state_of_charge": 64.0
    }
  },
  {
    "timestamp": "2026-07-10T11:20:01.476101",
    "values": {
      "sensor.pv_power": 3569.0,
      "sensor.active_power": -4.0,
      "sensor.house_consumption": 817.0,
      "sensor.battery_state_of_charge": 67.0
    }
  },
  {
    "timestamp": "2026-07-10T11:25:01.628473",
    "values": {
      "sensor.pv_power": 3663.0,
      "sensor.active_power": 36.0,
      "sensor.house_consumption": 532.0,
      "sensor.battery_state_of_charge": 70.0
    }
  },
  {
    "timestamp": "2026-07-10T11:30:04.989989",
    "values": {
      "sensor.pv_power": 3845.0,
      "sensor.active_power": 40.0,
      "sensor.house_consumption": 750.0,
      "sensor.battery_state_of_charge": 74.0
    }
  },
  {
    "timestamp": "2026-07-10T11:30:05.058833",
    "values": {
      "sensor.pv_power": 3845.0,
      "sensor.active_power": 40.0,
      "sensor.house_consumption": 750.0,
      "sensor.battery_state_of_charge": 74.0
    }
  },
  {
    "timestamp": "2026-07-10T11:35:01.729924",
    "values": {
      "sensor.pv_power": 3955.0,
      "sensor.active_power": -18.0,
      "sensor.house_consumption": 595.0,
      "sensor.battery_state_of_charge": 78.0
    }
  },
  {
    "timestamp": "2026-07-10T11:45:02.891689",
    "values": {
      "sensor.pv_power": 4153.0,
      "sensor.active_power": 44.0,
      "sensor.house_consumption": 978.0,
      "sensor.battery_state_of_charge": 84.0
    }
  },
  {
    "timestamp": "2026-07-10T11:45:03.001342",
    "values": {
      "sensor.pv_power": 4153.0,
      "sensor.active_power": 44.0,
      "sensor.house_consumption": 978.0,
      "sensor.battery_state_of_charge": 84.0
    }
  },
  {
    "timestamp": "2026-07-10T11:50:01.544006",
    "values": {
      "sensor.pv_power": 4226.0,
      "sensor.active_power": 34.0,
      "sensor.house_consumption": 610.0,
      "sensor.battery_state_of_charge": 88.0
    }
  },
  {
    "timestamp": "2026-07-10T11:55:01.606653",
    "values": {
      "sensor.pv_power": 4408.0,
      "sensor.active_power": 34.0,
      "sensor.house_consumption": 613.0,
      "sensor.battery_state_of_charge": 92.0
    }
  },
  {
    "timestamp": "2026-07-10T12:10:01.607529",
    "values": {
      "sensor.pv_power": 4712.0,
      "sensor.active_power": 3990.0,
      "sensor.house_consumption": 715.0,
      "sensor.battery_state_of_charge": 100.0
    }
  },
  {
    "timestamp": "2026-07-10T12:15:03.368445",
    "values": {
      "sensor.pv_power": 4765.0,
      "sensor.active_power": 2945.0,
      "sensor.house_consumption": 1816.0,
      "sensor.battery_state_of_charge": 100.0
    }
  },
  {
    "timestamp": "2026-07-10T12:20:03.432477",
    "values": {
      "sensor.pv_power": 4847.0,
      "sensor.active_power": 4292.0,
      "sensor.house_consumption": 557.0,
      "sensor.battery_state_of_charge": 100.0
    }
  },
  {
    "timestamp": "2026-07-10T12:25:02.417245",
    "values": {
      "sensor.pv_power": 4914.0,
      "sensor.active_power": 3357.0,
      "sensor.house_consumption": 1557.0,
      "sensor.battery_state_of_charge": 100.0
    }
  },
  {
    "timestamp": "2026-07-10T12:30:01.604540",
    "values": {
      "sensor.pv_power": 4980.0,
      "sensor.active_power": 2178.0,
      "sensor.house_consumption": 2806.0,
      "sensor.battery_state_of_charge": 100.0
    }
  },
  {
    "timestamp": "2026-07-10T12:30:01.647181",
    "values": {
      "sensor.pv_power": 4980.0,
      "sensor.active_power": 2178.0,
      "sensor.house_consumption": 2806.0,
      "sensor.battery_state_of_charge": 100.0
    }
  },
  {
    "timestamp": "2026-07-10T12:35:03.838871",
    "values": {
      "sensor.pv_power": 5061.0,
      "sensor.active_power": 2641.0,
      "sensor.house_consumption": 2427.0,
      "sensor.battery_state_of_charge": 100.0
    }
  },
  {
    "timestamp": "2026-07-10T12:40:01.850633",
    "values": {
      "sensor.pv_power": 5124.0,
      "sensor.active_power": 4131.0,
      "sensor.house_consumption": 1005.0,
      "sensor.battery_state_of_charge": 100.0
    }
  },
  {
    "timestamp": "2026-07-10T12:45:01.946741",
    "values": {
      "sensor.pv_power": 5211.0,
      "sensor.active_power": 3869.0,
      "sensor.house_consumption": 1351.0,
      "sensor.battery_state_of_charge": 100.0
    }
  },
  {
    "timestamp": "2026-07-10T12:45:01.971418",
    "values": {
      "sensor.pv_power": 5211.0,
      "sensor.active_power": 3869.0,
      "sensor.house_consumption": 1351.0,
      "sensor.battery_state_of_charge": 100.0
    }
  },
  {
    "timestamp": "2026-07-10T12:50:02.343747",
    "values": {
      "sensor.pv_power": 5234.0,
      "sensor.active_power": 3244.0,
      "sensor.house_consumption": 2011.0,
      "sensor.battery_state_of_charge": 100.0
    }
  },
  {
    "timestamp": "2026-07-10T12:55:02.363773",
    "values": {
      "sensor.pv_power": 5319.0,
      "sensor.active_power": 3747.0,
      "sensor.house_consumption": 1592.0,
      "sensor.battery_state_of_charge": 100.0
    }
  },
  {
    "timestamp": "2026-07-10T13:00:02.433393",
    "values": {
      "sensor.pv_power": 5358.0,
      "sensor.active_power": 3739.0,
      "sensor.house_consumption": 1636.0,
      "sensor.battery_state_of_charge": 100.0
    }
  },
  {
    "timestamp": "2026-07-10T13:00:02.483127",
    "values": {
      "sensor.pv_power": 5358.0,
      "sensor.active_power": 3739.0,
      "sensor.house_consumption": 1636.0,
      "sensor.battery_state_of_charge": 100.0
    }
  },
  {
    "timestamp": "2026-07-10T13:05:01.527424",
    "values": {
      "sensor.pv_power": 5427.0,
      "sensor.active_power": 4091.0,
      "sensor.house_consumption": 1351.0,
      "sensor.battery_state_of_charge": 100.0
    }
  },
  {
    "timestamp": "2026-07-10T13:10:02.187117",
    "values": {
      "sensor.pv_power": 5496.0,
      "sensor.active_power": 4097.0,
      "sensor.house_consumption": 1413.0,
      "sensor.battery_state_of_charge": 100.0
    }
  },
  {
    "timestamp": "2026-07-10T13:15:03.415127",
    "values": {
      "sensor.pv_power": 5503.0,
      "sensor.active_power": 3415.0,
      "sensor.house_consumption": 2100.0,
      "sensor.battery_state_of_charge": 100.0
    }
  },
  {
    "timestamp": "2026-07-10T13:15:03.499661",
    "values": {
      "sensor.pv_power": 5503.0,
      "sensor.active_power": 3415.0,
      "sensor.house_consumption": 2100.0,
      "sensor.battery_state_of_charge": 100.0
    }
  },
  {
    "timestamp": "2026-07-10T13:20:04.928935",
    "values": {
      "sensor.pv_power": 5556.0,
      "sensor.active_power": 4990.0,
      "sensor.house_consumption": 579.0,
      "sensor.battery_state_of_charge": 100.0
    }
  },
  {
    "timestamp": "2026-07-10T13:25:02.297667",
    "values": {
      "sensor.pv_power": 5616.0,
      "sensor.active_power": 5045.0,
      "sensor.house_consumption": 576.0,
      "sensor.battery_state_of_charge": 100.0
    }
  },
  {
    "timestamp": "2026-07-10T13:30:02.303474",
    "values": {
      "sensor.pv_power": 5674.0,
      "sensor.active_power": 5040.0,
      "sensor.house_consumption": 638.0,
      "sensor.battery_state_of_charge": 100.0
    }
  },
  {
    "timestamp": "2026-07-10T13:30:02.355530",
    "values": {
      "sensor.pv_power": 5674.0,
      "sensor.active_power": 5040.0,
      "sensor.house_consumption": 638.0,
      "sensor.battery_state_of_charge": 100.0
    }
  },
  {
    "timestamp": "2026-07-10T13:35:02.813568",
    "values": {
      "sensor.pv_power": 5697.0,
      "sensor.active_power": 5105.0,
      "sensor.house_consumption": 592.0,
      "sensor.battery_state_of_charge": 100.0
    }
  },
  {
    "timestamp": "2026-07-10T13:40:02.029526",
    "values": {
      "sensor.pv_power": 5763.0,
      "sensor.active_power": 5128.0,
      "sensor.house_consumption": 637.0,
      "sensor.battery_state_of_charge": 100.0
    }
  },
  {
    "timestamp": "2026-07-10T13:45:01.983864",
    "values": {
      "sensor.pv_power": 5791.0,
      "sensor.active_power": 5153.0,
      "sensor.house_consumption": 634.0,
      "sensor.battery_state_of_charge": 100.0
    }
  },
  {
    "timestamp": "2026-07-10T13:45:02.025618",
    "values": {
      "sensor.pv_power": 5791.0,
      "sensor.active_power": 5153.0,
      "sensor.house_consumption": 634.0,
      "sensor.battery_state_of_charge": 100.0
    }
  },
  {
    "timestamp": "2026-07-10T13:50:01.656364",
    "values": {
      "sensor.pv_power": 5819.0,
      "sensor.active_power": 5199.0,
      "sensor.house_consumption": 611.0,
      "sensor.battery_state_of_charge": 100.0
    }
  },
  {
    "timestamp": "2026-07-10T13:55:02.550109",
    "values": {
      "sensor.pv_power": 5823.0,
      "sensor.active_power": 5101.0,
      "sensor.house_consumption": 718.0,
      "sensor.battery_state_of_charge": 100.0
    }
  },
  {
    "timestamp": "2026-07-10T14:00:01.711376",
    "values": {
      "sensor.pv_power": 5842.0,
      "sensor.active_power": 5250.0,
      "sensor.house_consumption": 579.0,
      "sensor.battery_state_of_charge": 100.0
    }
  },
  {
    "timestamp": "2026-07-10T14:00:01.731299",
    "values": {
      "sensor.pv_power": 5842.0,
      "sensor.active_power": 5250.0,
      "sensor.house_consumption": 579.0,
      "sensor.battery_state_of_charge": 100.0
    }
  },
  {
    "timestamp": "2026-07-10T14:05:02.310629",
    "values": {
      "sensor.pv_power": 5903.0,
      "sensor.active_power": 5296.0,
      "sensor.house_consumption": 599.0,
      "sensor.battery_state_of_charge": 100.0
    }
  },
  {
    "timestamp": "2026-07-10T14:10:02.192498",
    "values": {
      "sensor.pv_power": 5888.0,
      "sensor.active_power": 5246.0,
      "sensor.house_consumption": 627.0,
      "sensor.battery_state_of_charge": 100.0
    }
  },
  {
    "timestamp": "2026-07-10T14:15:02.213508",
    "values": {
      "sensor.pv_power": 5913.0,
      "sensor.active_power": 5336.0,
      "sensor.house_consumption": 558.0,
      "sensor.battery_state_of_charge": 100.0
    }
  },
  {
    "timestamp": "2026-07-10T14:15:02.244701",
    "values": {
      "sensor.pv_power": 5913.0,
      "sensor.active_power": 5336.0,
      "sensor.house_consumption": 558.0,
      "sensor.battery_state_of_charge": 100.0
    }
  },
  {
    "timestamp": "2026-07-10T14:20:02.543298",
    "values": {
      "sensor.pv_power": 5914.0,
      "sensor.active_power": 5236.0,
      "sensor.house_consumption": 659.0,
      "sensor.battery_state_of_charge": 100.0
    }
  },
  {
    "timestamp": "2026-07-10T14:25:01.656517",
    "values": {
      "sensor.pv_power": 5938.0,
      "sensor.active_power": 5347.0,
      "sensor.house_consumption": 569.0,
      "sensor.battery_state_of_charge": 100.0
    }
  },
  {
    "timestamp": "2026-07-10T14:30:02.655260",
    "values": {
      "sensor.pv_power": 5940.0,
      "sensor.active_power": 5343.0,
      "sensor.house_consumption": 573.0,
      "sensor.battery_state_of_charge": 100.0
    }
  },
  {
    "timestamp": "2026-07-10T14:30:02.692154",
    "values": {
      "sensor.pv_power": 5940.0,
      "sensor.active_power": 5343.0,
      "sensor.house_consumption": 573.0,
      "sensor.battery_state_of_charge": 100.0
    }
  },
  {
    "timestamp": "2026-07-10T14:35:02.019757",
    "values": {
      "sensor.pv_power": 5965.0,
      "sensor.active_power": 1634.0,
      "sensor.house_consumption": 4311.0,
      "sensor.battery_state_of_charge": 100.0
    }
  },
  {
    "timestamp": "2026-07-10T14:40:03.010632",
    "values": {
      "sensor.pv_power": 5964.0,
      "sensor.active_power": 5300.0,
      "sensor.house_consumption": 645.0,
      "sensor.battery_state_of_charge": 100.0
    }
  },
  {
    "timestamp": "2026-07-10T14:45:02.255024",
    "values": {
      "sensor.pv_power": 5924.0,
      "sensor.active_power": 5151.0,
      "sensor.house_consumption": 749.0,
      "sensor.battery_state_of_charge": 100.0
    }
  },
  {
    "timestamp": "2026-07-10T14:45:02.287191",
    "values": {
      "sensor.pv_power": 5924.0,
      "sensor.active_power": 5151.0,
      "sensor.house_consumption": 749.0,
      "sensor.battery_state_of_charge": 100.0
    }
  },
  {
    "timestamp": "2026-07-10T14:50:02.561700",
    "values": {
      "sensor.pv_power": 5929.0,
      "sensor.active_power": 2425.0,
      "sensor.house_consumption": 3484.0,
      "sensor.battery_state_of_charge": 100.0
    }
  },
  {
    "timestamp": "2026-07-10T14:55:03.310220",
    "values": {
      "sensor.pv_power": 5939.0,
      "sensor.active_power": 2271.0,
      "sensor.house_consumption": 3645.0,
      "sensor.battery_state_of_charge": 100.0
    }
  },
  {
    "timestamp": "2026-07-10T15:00:02.391419",
    "values": {
      "sensor.pv_power": 5954.0,
      "sensor.active_power": 5015.0,
      "sensor.house_consumption": 919.0,
      "sensor.battery_state_of_charge": 100.0
    }
  },
  {
    "timestamp": "2026-07-10T15:00:02.428586",
    "values": {
      "sensor.pv_power": 5954.0,
      "sensor.active_power": 5015.0,
      "sensor.house_consumption": 919.0,
      "sensor.battery_state_of_charge": 100.0
    }
  },
  {
    "timestamp": "2026-07-10T15:05:02.002984",
    "values": {
      "sensor.pv_power": 5912.0,
      "sensor.active_power": 5102.0,
      "sensor.house_consumption": 790.0,
      "sensor.battery_state_of_charge": 100.0
    }
  },
  {
    "timestamp": "2026-07-10T15:10:02.089408",
    "values": {
      "sensor.pv_power": 5914.0,
      "sensor.active_power": 5018.0,
      "sensor.house_consumption": 877.0,
      "sensor.battery_state_of_charge": 100.0
    }
  },
  {
    "timestamp": "2026-07-10T15:15:01.626402",
    "values": {
      "sensor.pv_power": 5906.0,
      "sensor.active_power": 554.0,
      "sensor.house_consumption": 5330.0,
      "sensor.battery_state_of_charge": 100.0
    }
  },
  {
    "timestamp": "2026-07-10T15:15:01.655769",
    "values": {
      "sensor.pv_power": 5906.0,
      "sensor.active_power": 554.0,
      "sensor.house_consumption": 5330.0,
      "sensor.battery_state_of_charge": 100.0
    }
  },
  {
    "timestamp": "2026-07-10T15:20:03.073597",
    "values": {
      "sensor.pv_power": 5863.0,
      "sensor.active_power": 2883.0,
      "sensor.house_consumption": 2961.0,
      "sensor.battery_state_of_charge": 100.0
    }
  },
  {
    "timestamp": "2026-07-10T15:25:02.380784",
    "values": {
      "sensor.pv_power": 5869.0,
      "sensor.active_power": 5166.0,
      "sensor.house_consumption": 686.0,
      "sensor.battery_state_of_charge": 100.0
    }
  },
  {
    "timestamp": "2026-07-10T15:30:01.669443",
    "values": {
      "sensor.pv_power": 5840.0,
      "sensor.active_power": 4976.0,
      "sensor.house_consumption": 841.0,
      "sensor.battery_state_of_charge": 100.0
    }
  },
  {
    "timestamp": "2026-07-10T15:30:01.698026",
    "values": {
      "sensor.pv_power": 5840.0,
      "sensor.active_power": 4976.0,
      "sensor.house_consumption": 841.0,
      "sensor.battery_state_of_charge": 100.0
    }
  },
  {
    "timestamp": "2026-07-10T15:35:02.025955",
    "values": {
      "sensor.pv_power": 5810.0,
      "sensor.active_power": 2442.0,
      "sensor.house_consumption": 3348.0,
      "sensor.battery_state_of_charge": 100.0
    }
  },
  {
    "timestamp": "2026-07-10T15:40:02.089141",
    "values": {
      "sensor.pv_power": 5737.0,
      "sensor.active_power": 2148.0,
      "sensor.house_consumption": 3574.0,
      "sensor.battery_state_of_charge": 100.0
    }
  },
  {
    "timestamp": "2026-07-10T15:45:03.220022",
    "values": {
      "sensor.pv_power": 5744.0,
      "sensor.active_power": 4793.0,
      "sensor.house_consumption": 940.0,
      "sensor.battery_state_of_charge": 100.0
    }
  },
  {
    "timestamp": "2026-07-10T15:45:03.244181",
    "values": {
      "sensor.pv_power": 5744.0,
      "sensor.active_power": 4793.0,
      "sensor.house_consumption": 940.0,
      "sensor.battery_state_of_charge": 100.0
    }
  },
  {
    "timestamp": "2026-07-10T15:50:03.925471",
    "values": {
      "sensor.pv_power": 5713.0,
      "sensor.active_power": 2248.0,
      "sensor.house_consumption": 3454.0,
      "sensor.battery_state_of_charge": 100.0
    }
  },
  {
    "timestamp": "2026-07-10T15:55:01.515217",
    "values": {
      "sensor.pv_power": 5693.0,
      "sensor.active_power": 4837.0,
      "sensor.house_consumption": 837.0,
      "sensor.battery_state_of_charge": 100.0
    }
  },
  {
    "timestamp": "2026-07-10T16:00:01.692628",
    "values": {
      "sensor.pv_power": 5597.0,
      "sensor.active_power": 2229.0,
      "sensor.house_consumption": 3352.0,
      "sensor.battery_state_of_charge": 100.0
    }
  },
  {
    "timestamp": "2026-07-10T16:00:01.737094",
    "values": {
      "sensor.pv_power": 5597.0,
      "sensor.active_power": 2229.0,
      "sensor.house_consumption": 3352.0,
      "sensor.battery_state_of_charge": 100.0
    }
  },
  {
    "timestamp": "2026-07-10T16:05:02.210682",
    "values": {
      "sensor.pv_power": 5575.0,
      "sensor.active_power": 4639.0,
      "sensor.house_consumption": 920.0,
      "sensor.battery_state_of_charge": 100.0
    }
  },
  {
    "timestamp": "2026-07-10T16:10:02.314054",
    "values": {
      "sensor.pv_power": 5545.0,
      "sensor.active_power": 251.0,
      "sensor.house_consumption": 5272.0,
      "sensor.battery_state_of_charge": 100.0
    }
  },
  {
    "timestamp": "2026-07-10T16:15:02.366295",
    "values": {
      "sensor.pv_power": 5497.0,
      "sensor.active_power": 2830.0,
      "sensor.house_consumption": 2650.0,
      "sensor.battery_state_of_charge": 100.0
    }
  },
  {
    "timestamp": "2026-07-10T16:15:02.407699",
    "values": {
      "sensor.pv_power": 5497.0,
      "sensor.active_power": 2830.0,
      "sensor.house_consumption": 2650.0,
      "sensor.battery_state_of_charge": 100.0
    }
  },
  {
    "timestamp": "2026-07-10T16:20:01.875478",
    "values": {
      "sensor.pv_power": 5448.0,
      "sensor.active_power": 4711.0,
      "sensor.house_consumption": 719.0,
      "sensor.battery_state_of_charge": 100.0
    }
  },
  {
    "timestamp": "2026-07-10T16:25:01.928284",
    "values": {
      "sensor.pv_power": 5375.0,
      "sensor.active_power": 2102.0,
      "sensor.house_consumption": 3256.0,
      "sensor.battery_state_of_charge": 100.0
    }
  },
  {
    "timestamp": "2026-07-10T16:30:02.152555",
    "values": {
      "sensor.pv_power": 5302.0,
      "sensor.active_power": 4556.0,
      "sensor.house_consumption": 731.0,
      "sensor.battery_state_of_charge": 100.0
    }
  },
  {
    "timestamp": "2026-07-10T16:30:02.175861",
    "values": {
      "sensor.pv_power": 5302.0,
      "sensor.active_power": 4556.0,
      "sensor.house_consumption": 731.0,
      "sensor.battery_state_of_charge": 100.0
    }
  },
  {
    "timestamp": "2026-07-10T16:35:01.508072",
    "values": {
      "sensor.pv_power": 5263.0,
      "sensor.active_power": 4485.0,
      "sensor.house_consumption": 754.0,
      "sensor.battery_state_of_charge": 100.0
    }
  },
  {
    "timestamp": "2026-07-10T16:40:02.422740",
    "values": {
      "sensor.pv_power": 5216.0,
      "sensor.active_power": 1981.0,
      "sensor.house_consumption": 3210.0,
      "sensor.battery_state_of_charge": 100.0
    }
  },
  {
    "timestamp": "2026-07-10T16:45:02.428321",
    "values": {
      "sensor.pv_power": 5122.0,
      "sensor.active_power": 4460.0,
      "sensor.house_consumption": 628.0,
      "sensor.battery_state_of_charge": 100.0
    }
  },
  {
    "timestamp": "2026-07-10T16:45:02.462800",
    "values": {
      "sensor.pv_power": 5122.0,
      "sensor.active_power": 4460.0,
      "sensor.house_consumption": 628.0,
      "sensor.battery_state_of_charge": 100.0
    }
  },
  {
    "timestamp": "2026-07-10T16:50:01.915462",
    "values": {
      "sensor.pv_power": 5064.0,
      "sensor.active_power": 2109.0,
      "sensor.house_consumption": 2921.0,
      "sensor.battery_state_of_charge": 100.0
    }
  },
  {
    "timestamp": "2026-07-10T16:55:01.873983",
    "values": {
      "sensor.pv_power": 4994.0,
      "sensor.active_power": 4397.0,
      "sensor.house_consumption": 565.0,
      "sensor.battery_state_of_charge": 100.0
    }
  },
  {
    "timestamp": "2026-07-10T17:00:02.021433",
    "values": {
      "sensor.pv_power": 4926.0,
      "sensor.active_power": 1824.0,
      "sensor.house_consumption": 3076.0,
      "sensor.battery_state_of_charge": 100.0
    }
  },
  {
    "timestamp": "2026-07-10T17:00:02.057531",
    "values": {
      "sensor.pv_power": 4926.0,
      "sensor.active_power": 1824.0,
      "sensor.house_consumption": 3076.0,
      "sensor.battery_state_of_charge": 100.0
    }
  },
  {
    "timestamp": "2026-07-10T17:05:02.309016",
    "values": {
      "sensor.pv_power": 4815.0,
      "sensor.active_power": 4315.0,
      "sensor.house_consumption": 482.0,
      "sensor.battery_state_of_charge": 100.0
    }
  },
  {
    "timestamp": "2026-07-10T17:10:01.876366",
    "values": {
      "sensor.pv_power": 4740.0,
      "sensor.active_power": 4336.0,
      "sensor.house_consumption": 379.0,
      "sensor.battery_state_of_charge": 100.0
    }
  },
  {
    "timestamp": "2026-07-10T17:15:01.991019",
    "values": {
      "sensor.pv_power": 4661.0,
      "sensor.active_power": 4179.0,
      "sensor.house_consumption": 462.0,
      "sensor.battery_state_of_charge": 100.0
    }
  },
  {
    "timestamp": "2026-07-10T17:15:02.052272",
    "values": {
      "sensor.pv_power": 4661.0,
      "sensor.active_power": 4179.0,
      "sensor.house_consumption": 462.0,
      "sensor.battery_state_of_charge": 100.0
    }
  },
  {
    "timestamp": "2026-07-10T17:20:01.512935",
    "values": {
      "sensor.pv_power": 4573.0,
      "sensor.active_power": 4094.0,
      "sensor.house_consumption": 459.0,
      "sensor.battery_state_of_charge": 100.0
    }
  },
  {
    "timestamp": "2026-07-10T17:25:01.503088",
    "values": {
      "sensor.pv_power": 4492.0,
      "sensor.active_power": 3978.0,
      "sensor.house_consumption": 497.0,
      "sensor.battery_state_of_charge": 100.0
    }
  },
  {
    "timestamp": "2026-07-10T17:30:04.549060",
    "values": {
      "sensor.pv_power": 4408.0,
      "sensor.active_power": 3973.0,
      "sensor.house_consumption": 416.0,
      "sensor.battery_state_of_charge": 100.0
    }
  },
  {
    "timestamp": "2026-07-10T17:30:04.614180",
    "values": {
      "sensor.pv_power": 4408.0,
      "sensor.active_power": 3973.0,
      "sensor.house_consumption": 416.0,
      "sensor.battery_state_of_charge": 100.0
    }
  },
  {
    "timestamp": "2026-07-10T17:35:02.517031",
    "values": {
      "sensor.pv_power": 4299.0,
      "sensor.active_power": 3869.0,
      "sensor.house_consumption": 420.0,
      "sensor.battery_state_of_charge": 100.0
    }
  },
  {
    "timestamp": "2026-07-10T17:40:02.515981",
    "values": {
      "sensor.pv_power": 4230.0,
      "sensor.active_power": 3650.0,
      "sensor.house_consumption": 567.0,
      "sensor.battery_state_of_charge": 100.0
    }
  },
  {
    "timestamp": "2026-07-10T17:45:01.618684",
    "values": {
      "sensor.pv_power": 4131.0,
      "sensor.active_power": 3634.0,
      "sensor.house_consumption": 495.0,
      "sensor.battery_state_of_charge": 100.0
    }
  }
]